catalyst_sphinx_theme.py
catalyst_sphinx_theme/__init__.py
catalyst_sphinx_theme/breadcrumbs.html
catalyst_sphinx_theme/fonts.html
catalyst_sphinx_theme/footer.html
catalyst_sphinx_theme/layout.html
catalyst_sphinx_theme/search.html
catalyst_sphinx_theme/searchbox.html
catalyst_sphinx_theme/theme.conf
catalyst_sphinx_theme/theme_variables.jinja
catalyst_sphinx_theme/versions.html
catalyst_sphinx_theme/static/css/theme.css
catalyst_sphinx_theme/static/fonts/FreightSans/freight-sans-bold-italic.woff
catalyst_sphinx_theme/static/fonts/FreightSans/freight-sans-bold-italic.woff2
catalyst_sphinx_theme/static/fonts/FreightSans/freight-sans-bold.woff
catalyst_sphinx_theme/static/fonts/FreightSans/freight-sans-bold.woff2
catalyst_sphinx_theme/static/fonts/FreightSans/freight-sans-book-italic.woff
catalyst_sphinx_theme/static/fonts/FreightSans/freight-sans-book-italic.woff2
catalyst_sphinx_theme/static/fonts/FreightSans/freight-sans-book.woff
catalyst_sphinx_theme/static/fonts/FreightSans/freight-sans-book.woff2
catalyst_sphinx_theme/static/fonts/FreightSans/freight-sans-light-italic.woff
catalyst_sphinx_theme/static/fonts/FreightSans/freight-sans-light-italic.woff2
catalyst_sphinx_theme/static/fonts/FreightSans/freight-sans-light.woff
catalyst_sphinx_theme/static/fonts/FreightSans/freight-sans-light.woff2
catalyst_sphinx_theme/static/fonts/FreightSans/freight-sans-medium-italic.woff
catalyst_sphinx_theme/static/fonts/FreightSans/freight-sans-medium-italic.woff2
catalyst_sphinx_theme/static/fonts/FreightSans/freight-sans-medium.woff
catalyst_sphinx_theme/static/fonts/FreightSans/freight-sans-medium.woff2
catalyst_sphinx_theme/static/fonts/IBMPlexMono/IBMPlexMono-Light.woff
catalyst_sphinx_theme/static/fonts/IBMPlexMono/IBMPlexMono-Light.woff2
catalyst_sphinx_theme/static/fonts/IBMPlexMono/IBMPlexMono-Medium.woff
catalyst_sphinx_theme/static/fonts/IBMPlexMono/IBMPlexMono-Medium.woff2
catalyst_sphinx_theme/static/fonts/IBMPlexMono/IBMPlexMono-Regular.woff
catalyst_sphinx_theme-1.2.0.dist-info/LICENSE
catalyst_sphinx_theme-1.2.0.dist-info/METADATA
catalyst_sphinx_theme-1.2.0.dist-info/WHEEL
catalyst_sphinx_theme-1.2.0.dist-info/entry_points.txt
catalyst_sphinx_theme-1.2.0.dist-info/top_level.txt
catalyst_sphinx_theme-1.2.0.dist-info/RECORD
