Metadata-Version: 2.1
Name: catalyst-sphinx-theme
Version: 1.2.0
Summary: Catalyst Sphinx Theme
Home-page: https://github.com/catalyst-team/catalyst_sphinx_theme
Author: Artem Zolkin
Author-email: arquestro93@gmail.com
License: MIT License
Platform: UNKNOWN
Classifier: Programming Language :: Python :: 3
Classifier: Development Status :: 5 - Production/Stable
Classifier: Environment :: Web Environment
Classifier: Intended Audience :: Developers
Classifier: Intended Audience :: System Administrators
Classifier: License :: OSI Approved :: MIT License
Classifier: Operating System :: OS Independent
Classifier: Programming Language :: Python
Classifier: Topic :: Internet
Classifier: Topic :: Software Development :: Documentation
Requires-Python: >=3.6
Requires-Dist: sphinx
